boxoffice_api/__init__.py
boxoffice_api/boxoffice_app.py
boxoffice_api/test.py
boxoffice_api/validator.py
boxoffice_api-1.2.2.dist-info/LICENSE.md
boxoffice_api-1.2.2.dist-info/METADATA
boxoffice_api-1.2.2.dist-info/WHEEL
boxoffice_api-1.2.2.dist-info/top_level.txt
boxoffice_api-1.2.2.dist-info/RECORD
