Metadata-Version: 2.1
Name: boxoffice_api
Version: 1.2.2
Summary: Unofficial Python API for Box Office Mojo
Home-page: https://github.com/Stink-Po/boxoffice_api
Author: Pourya Mohamadi
Author-email: fresh.pourya@gmail.com
Keywords: python,movie,movies,boxoffice_api,box office,scraping
Classifier: Development Status :: 1 - Planning
Classifier: Intended Audience :: Developers
Classifier: Programming Language :: Python :: 3
Classifier: Operating System :: Unix
Classifier: Operating System :: MacOS :: MacOS X
Classifier: Operating System :: Microsoft :: Windows
Classifier: License :: OSI Approved :: MIT License
License-File: LICENSE.md
Requires-Dist: requests
Requires-Dist: bs4
Requires-Dist: pandas
